{"names":[{"id":"2920360","position":1,"name":"\u5317\u4eac\uff0c\u5929\u6d25\uff0c\u6cb3\u5317\u7701\uff0c\u5927\u8fde,\u4e0a\u6d77\uff0c\u6c5f\u82cf\u7701","scores":"27.1052"},{"id":"2917107","position":2,"name":"vgg","scores":"23.0831"},{"id":"2916914","position":3,"name":"jeider","scores":"22.0869"},{"id":"2916572","position":4,"name":"\u041e\u0447\u043a\u043e\u0434\u044b\u0440","scores":"22.0799"},{"id":"2916193","position":5,"name":"EEEE","scores":"22.0781"}],"comment": "List of v2.0.8, 2.0.9 "}