{"names":[{"id":"2696067","position":1,"name":"\u75af\u9b54\u88c2","scores":"21.1000"},{"id":"2696410","position":2,"name":"\u2623\ufe0f\/\/Yapper\/\/\u2623\ufe0f","scores":"17.0741"},{"id":"2699505","position":3,"name":"\u0410\u0440\u0441\u0435\u043d\u0438\u0439","scores":"17.0712"},{"id":"2699488","position":4,"name":"\u041c\u041e\u0413 \u042d\u043f\u0441\u0438\u043b\u043e\u043d-11","scores":"16.0621"},{"id":"2699161","position":5,"name":"\u0420\u0435\u0432\u0438\u0437\u043e\u0440","scores":"15.0643"}],"comment": "List of v2.0.4, 2.0.5, 2.0.6 "}